mpacklog/__init__.py
mpacklog/async_logger.py
mpacklog/log_server.py
mpacklog/read_log.py
mpacklog/serialize.py
mpacklog/sync_logger.py
mpacklog/utils.py
mpacklog/cli/__init__.py
mpacklog/cli/csv_printer.py
mpacklog/cli/field_printer.py
mpacklog/cli/fields.py
mpacklog/cli/json_printer.py
mpacklog/cli/main.py
mpacklog/cli/printer.py
mpacklog-4.0.1.dist-info/entry_points.txt
mpacklog-4.0.1.dist-info/LICENSE
mpacklog-4.0.1.dist-info/WHEEL
mpacklog-4.0.1.dist-info/METADATA
mpacklog-4.0.1.dist-info/RECORD
