Metadata-Version: 2.1
Name: mpacklog
Version: 4.0.1
Summary: Log dictionaries to file using the MessagePack serialization format.
Keywords: messagepack,serialization,logging
Author-email: Stéphane Caron <stephane.caron@normalesup.org>
Maintainer-email: Stéphane Caron <stephane.caron@normalesup.org>
Requires-Python: >=3.8
Classifier: Development Status :: 5 - Production/Stable
Classifier: Intended Audience :: Developers
Classifier: Intended Audience :: Science/Research
Classifier: License :: OSI Approved :: Apache Software License
Classifier: Operating System :: OS Independent
Classifier: Programming Language :: Python :: 3.8
Classifier: Programming Language :: Python :: 3.9
Classifier: Programming Language :: Python :: 3.10
Classifier: Programming Language :: Python :: 3.11
Classifier: Programming Language :: Python :: 3.12
Classifier: Topic :: Scientific/Engineering
Requires-Dist: aiofiles >= 0.7.0
Requires-Dist: loop-rate-limiters >= 1.0.0
Requires-Dist: msgpack >= 1.0.2
Project-URL: Changelog, https://github.com/stephane-caron/mpacklog.py/blob/master/CHANGELOG.md
Project-URL: Homepage, https://github.com/stephane-caron/mpacklog.py
Project-URL: Source, https://github.com/stephane-caron/mpacklog.py
Project-URL: Tracker, https://github.com/stephane-caron/mpacklog.py/issues
